<?xml version="1.0"?>
<methodCall>
    <methodName>LogIn</methodName>
    <params>
        <param>
            <value>
                <string></string>
            </value>
        </param>
        <param>
            <value>
                <string></string>
            </value>
        </param>
        <param>
            <value>
                <string></string>
            </value>
        </param>
        <param>
            <value>
                <string>OSTestUserAgentTemp</string>
            </value>
        </param>
    </params>
</methodCall>
